{
  "type": "mysticalagriculture:infusion",
  "input": {
    "item": "mysticalmorecrops:blank_egg"
  },
  "conditions": [
    {
      "type": "mysticalagriculture:crop_enabled",
      "crop": "mysticalmorecrops:golem"
    },
    {
      "type": "mysticalagriculture:crop_enabled",
      "crop": "mysticalagriculture:ice"
    }
  ],
  "ingredients": [
    {
      "item": "minecraft:snowball"
    },
    {
      "item": "mysticalagriculture:golem_essence"
    },
    {
      "item": "mysticalagriculture:experience_droplet"
    },
    {
      "item": "mysticalagriculture:ice_essence"
    },
    {
      "item": "minecraft:snowball"
    },
    {
      "item": "mysticalagriculture:golem_essence"
    },
    {
      "item": "mysticalagriculture:experience_droplet"
    },
    {
      "item": "mysticalagriculture:ice_essence"
    }
  ],
  "result": {
    "item": "minecraft:snow_golem_spawn_egg"
  }
}